workday_mcp_new/__init__.py
workday_mcp_new/server.py
workday_mcp_new-0.1.0.dist-info/METADATA
workday_mcp_new-0.1.0.dist-info/WHEEL
workday_mcp_new-0.1.0.dist-info/entry_points.txt
workday_mcp_new-0.1.0.dist-info/RECORD
