Metadata-Version: 2.4
Name: workday-mcp-new
Version: 0.1.0
Summary: WORKDAY is an HRMS tool
Author-email: nandishad <nandisha.d@think41.com>
Requires-Python: >=3.10
Requires-Dist: mcp>=1.6.0
Requires-Dist: requests>=2.32.3
